llm_schema_lite/__init__.py
llm_schema_lite/core.py
llm_schema_lite/exceptions.py
llm_schema_lite/py.typed
llm_schema_lite/dspy_integration/README.md
llm_schema_lite/dspy_integration/__init__.py
llm_schema_lite/dspy_integration/adapters/__init__.py
llm_schema_lite/dspy_integration/adapters/structured_output_adapter.py
llm_schema_lite/formatters/__init__.py
llm_schema_lite/formatters/base.py
llm_schema_lite/formatters/jsonish_formatter.py
llm_schema_lite/formatters/typescript_formatter.py
llm_schema_lite/formatters/yaml_formatter.py
llm_schema_lite-0.6.0.dist-info/METADATA
llm_schema_lite-0.6.0.dist-info/WHEEL
llm_schema_lite-0.6.0.dist-info/licenses/LICENSE
llm_schema_lite-0.6.0.dist-info/RECORD
