Metadata-Version: 2.4
Name: llm-schema-lite
Version: 0.6.0
Summary: LLM-ify your JSON schemas
Project-URL: Homepage, https://github.com/rohitgarud/llm-schema-lite
Project-URL: Repository, https://github.com/rohitgarud/llm-schema-lite
Project-URL: Issues, https://github.com/rohitgarud/llm-schema-lite/issues
Project-URL: Documentation, https://github.com/rohitgarud/llm-schema-lite#readme
Project-URL: Changelog, https://github.com/rohitgarud/llm-schema-lite/blob/main/CHANGELOG.md
Author-email: Rohit Garud <rohit.garuda1992@gmail.com>
Maintainer-email: Rohit Garud <rohit.garuda1992@gmail.com>
License: MIT License
License-File: LICENSE
Keywords: dspy,json-schema,llm,openai,pydantic,schema,token-optimization
Classifier: Development Status :: 3 - Alpha
Classifier: Intended Audience :: Developers
Classifier: License :: OSI Approved :: MIT License
Classifier: Programming Language :: Python :: 3
Classifier: Programming Language :: Python :: 3.10
Classifier: Programming Language :: Python :: 3.11
Classifier: Programming Language :: Python :: 3.12
Classifier: Programming Language :: Python :: 3.13
Classifier: Topic :: Internet :: WWW/HTTP :: Dynamic Content
Classifier: Topic :: Scientific/Engineering :: Artificial Intelligence
Classifier: Topic :: Software Development :: Libraries :: Python Modules
Classifier: Typing :: Typed
Requires-Python: >=3.10
Requires-Dist: json-repair>=0.7.0
Requires-Dist: jsonschema>=4.20.0
Requires-Dist: pydantic[email]>=2.10.0
Requires-Dist: pyyaml>=6.0.3
Requires-Dist: regex>=2023.0.0
Requires-Dist: tiktoken>=0.12.0
Provides-Extra: benchmark
Requires-Dist: datasets>=4.2.0; extra == 'benchmark'
Provides-Extra: dev
Requires-Dist: bandit[toml]>=1.7.10; extra == 'dev'
Requires-Dist: commitlint>=1.3.0; extra == 'dev'
Requires-Dist: coverage>=7.6.0; extra == 'dev'
Requires-Dist: git-changelog>=2.5.0; extra == 'dev'
Requires-Dist: gitlint>=0.19.0; extra == 'dev'
Requires-Dist: mypy>=1.13.0; extra == 'dev'
Requires-Dist: pre-commit>=4.0.0; extra == 'dev'
Requires-Dist: psutil>=7.1.1; extra == 'dev'
Requires-Dist: pytest-cov>=6.0.0; extra == 'dev'
Requires-Dist: pytest-xdist>=3.6.0; extra == 'dev'
Requires-Dist: pytest>=8.3.0; extra == 'dev'
Requires-Dist: ruff>=0.8.0; extra == 'dev'
Requires-Dist: types-requests>=2.32.0; extra == 'dev'
Provides-Extra: dspy
Requires-Dist: dspy>=3.0.3; extra == 'dspy'
